heal_check/__init__.py
heal_check/exceptions.py
heal_check-0.10.0.dist-info/LICENSE
heal_check-0.10.0.dist-info/METADATA
heal_check-0.10.0.dist-info/WHEEL
heal_check-0.10.0.dist-info/top_level.txt
heal_check-0.10.0.dist-info/RECORD
